clerk.py
faxter_clerk/__init__.py
faxter_clerk/__main__.py
faxter_clerk/clerk.py
faxter_clerk/setup.py
faxter_clerk-1.0.0.dist-info/licenses/LICENSE
faxter_clerk-1.0.0.dist-info/METADATA
faxter_clerk-1.0.0.dist-info/WHEEL
faxter_clerk-1.0.0.dist-info/entry_points.txt
faxter_clerk-1.0.0.dist-info/top_level.txt
faxter_clerk-1.0.0.dist-info/RECORD
