Metadata-Version: 2.4
Name: faxter-clerk
Version: 1.0.0
Summary: Command-line interface for AI Accounting OS - Talk to your books like you're texting a friend
Home-page: https://ai.faxter.com
Author: AI Accounting Team
Author-email: AI Accounting Team <support@faxter.com>
License: MIT
Project-URL: Homepage, https://ai.faxter.com
Project-URL: Documentation, https://github.com/yourusername/ai-accounting-cli#readme
Project-URL: Repository, https://github.com/yourusername/ai-accounting-cli
Project-URL: Bug Tracker, https://github.com/yourusername/ai-accounting-cli/issues
Keywords: accounting,ai,cli,finance,bookkeeping,natural-language
Classifier: Development Status :: 4 - Beta
Classifier: Intended Audience :: Financial and Insurance Industry
Classifier: Intended Audience :: End Users/Desktop
Classifier: Topic :: Office/Business :: Financial :: Accounting
Classifier: License :: OSI Approved :: MIT License
Classifier: Programming Language :: Python :: 3
Classifier: Programming Language :: Python :: 3.8
Classifier: Programming Language :: Python :: 3.9
Classifier: Programming Language :: Python :: 3.10
Classifier: Programming Language :: Python :: 3.11
Classifier: Programming Language :: Python :: 3.12
Classifier: Operating System :: OS Independent
Classifier: Environment :: Console
Requires-Python: >=3.8
License-File: LICENSE
Requires-Dist: requests>=2.28.0
Provides-Extra: rich
Requires-Dist: rich>=13.0.0; extra == "rich"
Provides-Extra: sse
Requires-Dist: sseclient-py>=1.7.0; extra == "sse"
Provides-Extra: full
Requires-Dist: rich>=13.0.0; extra == "full"
Requires-Dist: sseclient-py>=1.7.0; extra == "full"
Dynamic: author
Dynamic: home-page
Dynamic: license-file
Dynamic: requires-python
